setup.cfg
setup.py
utilum/__init__.py
utilum/array.py
utilum/attribute.py
utilum/database.py
utilum/dicts.py
utilum/file.py
utilum/formadator.py
utilum/http.py
utilum/json.py
utilum/logger.py
utilum/output.py
utilum/shredder.py
utilum/string.py
utilum/system.py
utilum/time.py
utilum/token.py
utilum/url.py
utilum.egg-info/PKG-INFO
utilum.egg-info/SOURCES.txt
utilum.egg-info/dependency_links.txt
utilum.egg-info/not-zip-safe
utilum.egg-info/top_level.txt
utilum/lookup/__init__.py
utilum/lookup/extension.py
utilum/lookup/http.py