Metadata-Version: 1.0
Name: utilum
Version: 0.1.3
Summary: Basic Utilities Package
Home-page: UNKNOWN
Author: UNKNOWN
Author-email: UNKNOWN
License: UNKNOWN
Platform: UNKNOWN
